rms_rabbit/__init__.py
rms_rabbit/base_handler.py
rms_rabbit/config.py
rms_rabbit/connectors.py
rms_rabbit/consumer.py
rms_rabbit/datatypes.py
rms_rabbit/errors.py
rms_rabbit/publisher.py
rms_rabbit/rabbit_app.py
rms_rabbit/schemas.py
rms_rabbit/serializers.py
rms_rabbit-1.0.0.dist-info/METADATA
rms_rabbit-1.0.0.dist-info/WHEEL
rms_rabbit-1.0.0.dist-info/top_level.txt
rms_rabbit-1.0.0.dist-info/RECORD
