Metadata-Version: 2.1
Name: rms-rabbit
Version: 1.0.0
Summary: Библиотека для работы с очередями
Home-page: https://gitlab.com/requirements-managment-systems/rms_rabbit
Author: Prokofev Danil
Author-email: skily02@gmail.com
Platform: linux/x86_64
Platform: arm64
Platform: win64
Platform: win32
Requires-Python: >=3.11
Requires-Dist: aio-pika==9.5.4
Requires-Dist: marshmallow-enum<2,>=1.5
Requires-Dist: marshmallow-dataclass<8.8,>=8.4
Requires-Dist: orjson<4.0.0,>=3.0.0
Requires-Dist: pyhocon<1,>=0.3.57
Requires-Dist: typeguard==4.4.3
Requires-Dist: setuptools<81.0.0,>=65.5.0
